MANIFEST.in
dockontext/__init__.py
dockontext/dockontext.py
dockontext/dockontext.pyi
dockontext/py.typed
dockontext-0.1.3.dist-info/LICENSE
dockontext-0.1.3.dist-info/WHEEL
dockontext-0.1.3.dist-info/METADATA
dockontext-0.1.3.dist-info/RECORD
