Metadata-Version: 2.1
Name: dockontext
Version: 0.1.3
Summary: context manager that runs and closes docker containers
Home-page: https://github.com/ghsang/dockontext
License: MIT
Keywords: docker
Author: Hyuksang Gwon
Author-email: gwonhyuksang@gmail.com
Requires-Python: >=3.7,<4.0
Classifier: License :: OSI Approved :: MIT License
Classifier: Programming Language :: Python :: 3
Classifier: Programming Language :: Python :: 3.7
Classifier: Programming Language :: Python :: 3.8
Project-URL: Repository, https://github.com/ghsang/dockontext
